cad_viewer_widget/__init__.py
cad_viewer_widget/_version.py
cad_viewer_widget/sidecar.py
cad_viewer_widget/utils.py
cad_viewer_widget/widget.py
cad_viewer_widget-3.0.2.data/data/share/jupyter/labextensions/cad-viewer-widget/package.json
cad_viewer_widget-3.0.2.data/data/share/jupyter/labextensions/cad-viewer-widget/static/103.d0a23e85720bb459596e.js
cad_viewer_widget-3.0.2.data/data/share/jupyter/labextensions/cad-viewer-widget/static/194.0c7929627009ab78fbf3.js
cad_viewer_widget-3.0.2.data/data/share/jupyter/labextensions/cad-viewer-widget/static/194.0c7929627009ab78fbf3.js.LICENSE.txt
cad_viewer_widget-3.0.2.data/data/share/jupyter/labextensions/cad-viewer-widget/static/27.035daecb764f61ba828d.js
cad_viewer_widget-3.0.2.data/data/share/jupyter/labextensions/cad-viewer-widget/static/493.769961ecd96c52067523.js
cad_viewer_widget-3.0.2.data/data/share/jupyter/labextensions/cad-viewer-widget/static/509.f3f58925424879fd54ab.js
cad_viewer_widget-3.0.2.data/data/share/jupyter/labextensions/cad-viewer-widget/static/760.c69e67f23ee1b30c0f04.js
cad_viewer_widget-3.0.2.data/data/share/jupyter/labextensions/cad-viewer-widget/static/852.0fdf77472dbea6527b16.js
cad_viewer_widget-3.0.2.data/data/share/jupyter/labextensions/cad-viewer-widget/static/882.b605618135107f7c2d18.js
cad_viewer_widget-3.0.2.data/data/share/jupyter/labextensions/cad-viewer-widget/static/965.782feb1da9e2ce58bbc4.js
cad_viewer_widget-3.0.2.data/data/share/jupyter/labextensions/cad-viewer-widget/static/965.782feb1da9e2ce58bbc4.js.LICENSE.txt
cad_viewer_widget-3.0.2.data/data/share/jupyter/labextensions/cad-viewer-widget/static/remoteEntry.1ad5770e16800f5d3c93.js
cad_viewer_widget-3.0.2.data/data/share/jupyter/labextensions/cad-viewer-widget/static/style.js
cad_viewer_widget-3.0.2.data/data/share/jupyter/labextensions/cad-viewer-widget/static/third-party-licenses.json
cad_viewer_widget-3.0.2.data/data/share/jupyter/labextensions/cad-viewer-widget/install.json
cad_viewer_widget-3.0.2.dist-info/METADATA
cad_viewer_widget-3.0.2.dist-info/WHEEL
cad_viewer_widget-3.0.2.dist-info/licenses/LICENSE
cad_viewer_widget-3.0.2.dist-info/RECORD
