Metadata-Version: 2.4
Name: cad_viewer_widget
Version: 3.0.2
Dynamic: Keywords
Summary: A Jupyter widget to view cad objects
Project-URL: Repository, https://github.com/bernhard-42/cad-viewer-widget.git
Author-email: Bernhard Walter <b_waltrer@arcor.de>
License: Copyright (c) 2021 Bernhard Walter
License-File: LICENSE
Classifier: Framework :: Jupyter
Classifier: Framework :: Jupyter :: JupyterLab
Classifier: Framework :: Jupyter :: JupyterLab :: 4
Classifier: Framework :: Jupyter :: JupyterLab :: Extensions
Classifier: Framework :: Jupyter :: JupyterLab :: Extensions :: Prebuilt
Classifier: License :: OSI Approved :: BSD License
Classifier: Programming Language :: Python
Classifier: Programming Language :: Python :: 3
Classifier: Programming Language :: Python :: 3.10
Classifier: Programming Language :: Python :: 3.11
Classifier: Programming Language :: Python :: 3.12
Classifier: Programming Language :: Python :: 3.13
Requires-Python: >=3.8
Requires-Dist: ipywidgets~=8.1.5
Requires-Dist: jupyterlab~=4.4.0
Requires-Dist: numpy
Requires-Dist: pyparsing
